myapp/__init__.py
myapp/admin.py
myapp/admin_views.py
myapp/apps.py
myapp/context_processors.py
myapp/forms.py
myapp/models.py
myapp/tests.py
myapp/urls.py
myapp/views.py
myapp/assets/coverhero.jpg
myapp/assets/band-member-photos/buckethead.jpg
myapp/assets/band-member-photos/jaco.jpg
myapp/assets/band-member-photos/jj.jpg
myapp/assets/band-member-photos/jz.jpg
myapp/assets/concert-photos/Montreaux.jpeg
myapp/assets/concert-photos/aliceinchains.jpg
myapp/assets/concert-photos/meshuggah.jpg
myapp/assets/shop-photos/bracelet.jpg
myapp/assets/shop-photos/cattledecap.jpg
myapp/assets/shop-photos/kissfridge.jpeg
myapp/assets/shop-photos/kisskasket.jpg
myapp/assets/shop-photos/mudvayneposter.jpg
myapp/assets/shop-photos/toolstickers.jpg
myapp/migrations/0001_initial.py
myapp/migrations/0002_bandmember_concert_emaillist.py
myapp/migrations/0003_bandmember_photo_url_concert_cover_photo_url_and_more.py
myapp/migrations/0004_emaillist_first_name.py
myapp/migrations/0005_inquiry.py
myapp/migrations/0006_clear_emaillist.py
myapp/migrations/0007_clear_emaillist.py
myapp/migrations/0008_emaillist.py
myapp/migrations/__init__.py
myapp/stylesheets/concerts.css
myapp/stylesheets/send_newsletter.css
myapp/templates/base.html
myapp/templates/cart.html
myapp/templates/checkout_success.html
myapp/templates/concerts.html
myapp/templates/contact.html
myapp/templates/home.html
myapp/templates/news.html
myapp/templates/newsletter-email-template.html
myapp/templates/shop.html
myapp/templates/unsubscribe_confirm.html
myapp/templates/admin/index.html
myapp/templates/admin/send_newsletter.html
myapp/templatetags/__init__.py
myapp/templatetags/discount_tags.py
myapp/templatetags/form_tags.py
myapp/templatetags/__pycache__/__init__.cpython-312.pyc
myapp/templatetags/__pycache__/discount_tags.cpython-312.pyc
myapp/templatetags/__pycache__/form_tags.cpython-312.pyc
myproject/__init__.py
myproject/asgi.py
myproject/cli.py
myproject/settings.py
myproject/urls.py
myproject/wsgi.py
band_landing_page_webshop-1.0.0.dist-info/METADATA
band_landing_page_webshop-1.0.0.dist-info/WHEEL
band_landing_page_webshop-1.0.0.dist-info/entry_points.txt
band_landing_page_webshop-1.0.0.dist-info/top_level.txt
band_landing_page_webshop-1.0.0.dist-info/RECORD
