Metadata-Version: 2.4
Name: band-landing-page-webshop
Version: 1.0.0
Summary: A full Django project packaged for installation
Author: Robert Nagy
License: MIT
Requires-Dist: Django==5.1.7
Requires-Dist: python-decouple==3.8
Requires-Dist: stripe==12.0.0
Requires-Dist: sqlparse==0.5.3
